{
    "last_cuisines": [
        "Meksykańska (Cantina)",
        "Turecka (Kebab/Meze)",
        "Francuska (Prowansalska)",
        "Smak Jesieni (Dyniowe/Grzybowe)",
        "Peruwiańska",
        "Wietnamska (Street Food)",
        "Ukraińska (Wareniki/Barszcz)",
        "Argentyńska",
        "Babcina Kuchnia (Comfort Food)",
        "Hiszpańska (Tapas/Paella)",
        "Turecka (Kebab/Meze)",
        "Babcina Kuchnia (Comfort Food)",
        "Indyjska (Curry House)",
        "Brazylijska",
        "Smak Jesieni (Dyniowe/Grzybowe)"
    ],
    "last_regions": [
        "Ameryki",
        "Azja"
    ],
    "last_poll": {
        "message_id": 1462713061671567411,
        "options": [
            "Taco Quesadilla Fusion",
            "Carpaccio z Meksykańską Zazieleniną",
            "Gazpacho z Meksykańskim Akcentem"
        ]
    }
}